aria2_rpc_client/__init__.py
aria2_rpc_client/client.py
aria2_rpc_client/connection.py
aria2_rpc_client/exceptions.py
aria2_rpc_client/options.py
aria2_rpc_client/types.py
aria2_rpc_client-0.5.0.dist-info/METADATA
aria2_rpc_client-0.5.0.dist-info/WHEEL
aria2_rpc_client-0.5.0.dist-info/RECORD
